nexon/__init__.py
nexon/__main__.py
nexon/abc.py
nexon/activity.py
nexon/appinfo.py
nexon/application_command.py
nexon/asset.py
nexon/audit_logs.py
nexon/auto_moderation.py
nexon/backoff.py
nexon/badge.py
nexon/bans.py
nexon/bin/COPYING
nexon/bin/libopus-0.x64.dll
nexon/bin/libopus-0.x86.dll
nexon/channel.py
nexon/client.py
nexon/colour.py
nexon/components.py
nexon/context_managers.py
nexon/data/__init__.py
nexon/data/user.py
nexon/dataManager.py
nexon/embeds.py
nexon/emoji.py
nexon/enums.py
nexon/errors.py
nexon/ext/application_checks/__init__.py
nexon/ext/application_checks/core.py
nexon/ext/application_checks/errors.py
nexon/ext/application_checks/py.typed
nexon/ext/commands/__init__.py
nexon/ext/commands/_types.py
nexon/ext/commands/bot.py
nexon/ext/commands/cog.py
nexon/ext/commands/context.py
nexon/ext/commands/converter.py
nexon/ext/commands/cooldowns.py
nexon/ext/commands/core.py
nexon/ext/commands/errors.py
nexon/ext/commands/flags.py
nexon/ext/commands/help.py
nexon/ext/commands/py.typed
nexon/ext/commands/view.py
nexon/ext/slash_utils/__init__.py
nexon/ext/slash_utils/py.typed
nexon/ext/slash_utils/slash.py
nexon/ext/tasks/__init__.py
nexon/ext/tasks/py.typed
nexon/file.py
nexon/flags.py
nexon/gateway.py
nexon/guild.py
nexon/guild_preview.py
nexon/http.py
nexon/integrations.py
nexon/interactions.py
nexon/invite.py
nexon/iterators.py
nexon/member.py
nexon/mentions.py
nexon/message.py
nexon/mixins.py
nexon/object.py
nexon/oggparse.py
nexon/opus.py
nexon/partial_emoji.py
nexon/permissions.py
nexon/player.py
nexon/py.typed
nexon/raw_models.py
nexon/reaction.py
nexon/role.py
nexon/role_connections.py
nexon/scheduled_events.py
nexon/shard.py
nexon/stage_instance.py
nexon/state.py
nexon/sticker.py
nexon/team.py
nexon/template.py
nexon/threads.py
nexon/types/__init__.py
nexon/types/activity.py
nexon/types/appinfo.py
nexon/types/audit_log.py
nexon/types/auto_moderation.py
nexon/types/channel.py
nexon/types/checks.py
nexon/types/components.py
nexon/types/embed.py
nexon-0.2.3.dist-info/LICENSE
nexon-0.2.3.dist-info/METADATA
nexon-0.2.3.dist-info/WHEEL
nexon-0.2.3.dist-info/RECORD
