Metadata-Version: 2.3
Name: nexon
Version: 0.2.3
Summary: A Python wrapper for the Discord API forked from nextcord with additional stuff
License: MIT
Author: MahiroX36
Requires-Python: >=3.12,<4.0
Classifier: Development Status :: 5 - Production/Stable
Classifier: Framework :: AsyncIO
Classifier: Framework :: aiohttp
Classifier: Intended Audience :: Developers
Classifier: License :: OSI Approved :: MIT License
Classifier: Natural Language :: English
Classifier: Operating System :: OS Independent
Classifier: Programming Language :: Python :: 3
Classifier: Programming Language :: Python :: 3.12
Classifier: Programming Language :: Python :: 3.13
Classifier: Topic :: Internet
Classifier: Topic :: Software Development :: Libraries
Classifier: Topic :: Software Development :: Libraries :: Python Modules
Classifier: Topic :: Utilities
Classifier: Typing :: Typed
Provides-Extra: speed
Provides-Extra: voice
Requires-Dist: Brotli ; (platform_python_implementation == "CPython") and (extra == "speed")
Requires-Dist: PyNaCl (>=1.3.0,<1.5) ; extra == "voice"
Requires-Dist: aiodns (>1.1) ; (sys_platform == "linux" or sys_platform == "darwin") and (extra == "speed")
Requires-Dist: aiohttp (>=3.8.0,<4.0.0)
Requires-Dist: audioop-lts (>=0.2.1,<0.3.0) ; python_version >= "3.13" and python_version < "4.0"
Requires-Dist: brotlicffi ; (platform_python_implementation != "CPython") and (extra == "speed")
Requires-Dist: emoji
Requires-Dist: orjson (>=3.5.4) ; extra == "speed"
Requires-Dist: rich
Requires-Dist: typing_extensions (>=4.2.0,<5.0.0)
Project-URL: Documentation, https://docs.nextcord.dev/
Project-URL: Homepage, https://github.com/mahirox36/nexon
Project-URL: Issue tracker, https://github.com/nexon/nexon/issues
